paramBundle.py
paramBundle-0.50.dist-info/LICENSE
paramBundle-0.50.dist-info/METADATA
paramBundle-0.50.dist-info/WHEEL
paramBundle-0.50.dist-info/top_level.txt
paramBundle-0.50.dist-info/RECORD
