Metadata-Version: 2.1
Name: paramBundle
Version: 0.50
Summary: Automatically select, check and bundle keyword arguments from 'kwargs' dictionaries
Home-page: https://www.blackward.de
Author: Dominik Niedenzu
Author-email: pyadaaah@blackward.de
Maintainer: Dominik Niedenzu
License: Proprietary License
Platform: any platform which provides python
Classifier: Development Status :: 3 - Alpha
Classifier: Intended Audience :: Developers
Classifier: Intended Audience :: Education
Classifier: Intended Audience :: Science/Research
Classifier: Intended Audience :: Other Audience
Classifier: License :: Other/Proprietary License
Classifier: Operating System :: OS Independent
Classifier: Programming Language :: Python
Classifier: Topic :: Software Development
Requires-Python: >= 2.2
License-File: LICENSE
